Metadata-Version: 2.1
Name: secrets-safe-library
Version: 7.0
Summary: Password Safe API integration written in Python, Abstract complexity of managing secrets with the API.
Author: BeyondTrust Corporation
Author-email: support@beyondtrust.com
License: MIT License
Project-URL: support, https://www.beyondtrust.com/docs/index.htm#support
Keywords: beyondtrust,devops,secrets,secretssafe,security
Classifier: Programming Language :: Python :: 3
Classifier: License :: OSI Approved :: MIT License
Requires-Python: >=3.11
License-File: LICENSE
Requires-Dist: requests==2.32.3
Requires-Dist: retry-requests==2.0.0
Requires-Dist: cryptography==43.0.1
Requires-Dist: Cerberus==1.3.5
